MANIFEST.in
VERSION
requirements.txt
setup.py
examples/client.py
examples/credentials.py
examples/debug.py
examples/service.py
unimatrix.ext.agent.egg-info/PKG-INFO
unimatrix.ext.agent.egg-info/SOURCES.txt
unimatrix.ext.agent.egg-info/dependency_links.txt
unimatrix.ext.agent.egg-info/entry_points.txt
unimatrix.ext.agent.egg-info/requires.txt
unimatrix.ext.agent.egg-info/top_level.txt
unimatrix/ext/agent/__init__.py
unimatrix/ext/agent/__unimatrix__.py
unimatrix/ext/agent/client.py
unimatrix/ext/agent/iprincipal.py
unimatrix/ext/agent/package.json
unimatrix/ext/agent/tokenexchangeservice.py
unimatrix/ext/agent/trusttoken.py
unimatrix/ext/agent/credentials/__init__.py
unimatrix/ext/agent/credentials/accesstoken.py
unimatrix/ext/agent/credentials/agent.py
unimatrix/ext/agent/credentials/default.py
unimatrix/ext/agent/credentials/iaccesstoken.py
unimatrix/ext/agent/credentials/icredentials.py
unimatrix/ext/agent/credentials/session.py
unimatrix/ext/agent/permissions/__init__.py
unimatrix/ext/agent/permissions/irequest.py
unimatrix/ext/agent/permissions/tests/__init__.py
unimatrix/ext/agent/permissions/tests/test_unit_permissions_agent.py
unimatrix/ext/agent/signer/__init__.py
unimatrix/ext/agent/signer/debug.py
unimatrix/ext/agent/signer/default.py
unimatrix/ext/agent/signer/itokensigner.py